djeu/__init__.py
djeu/apps.py
djeu/conf.py
djeu/signals.py
djeu/translation.py
djeu/urls.py
djeu/views.py
djeu/admin/__init__.py
djeu/db/__init__.py
djeu/db/models/__init__.py
djeu/db/models/fields/__init__.py
djeu/db/models/fields/image_pyramid_field.py
djeu/db/models/fields/julian_date_field.py
djeu/db/models/fields/partial_date_field.py
djeu/db/models/fields/related/__init__.py
djeu/db/models/fields/related/extended_foreign_key.py
djeu/db/models/fields/related/extended_many_to_many_field.py
djeu/db/models/fields/related/nationality_foreign_key.py
djeu/forms/__init__.py
djeu/forms/extended_model_choice_field.py
djeu/forms/extended_model_multiple_choice_field.py
djeu/forms/julian_date_field.py
djeu/forms/nationality_model_choice_field.py
djeu/forms/partial_date_field.py
djeu/forms/widgets/__init__.py
djeu/forms/widgets/date_picker_input.py
djeu/forms/widgets/extended_autocomplete_select.py
djeu/forms/widgets/extended_autocomplete_select_multiply.py
djeu/forms/widgets/julian_date_picker_input.py
djeu/forms/widgets/linked_file_input.py
djeu/forms/widgets/nationality_autocomplete_select.py
djeu/forms/widgets/partial_date_picker_input.py
djeu/forms/widgets/pdf_viewer_input.py
djeu/locale/ru_RU/LC_MESSAGES/.keep
djeu/migrations/__init__.py
djeu/models/__init__.py
djeu/static/djeu/css/autocomplete.mod.css
djeu/static/djeu/css/filepicker.default.css
djeu/static/djeu/css/jquery-extended-autocomplete-select-multiply.css
djeu/static/djeu/css/jquery-nationality-autocomplete-select-multiply.css
djeu/static/djeu/css/jquery-pdf-viewer.default.css
djeu/static/djeu/css/jquery-pdf-viewer.default.css.map
djeu/static/djeu/css/jquery-pdf-viewer.default.min.css
djeu/static/djeu/css/jquery-pdf-viewer.default.min.css.map
djeu/static/djeu/css/nationality-autocomplete.mod.css
djeu/static/djeu/css/jquery-calendars/flora.calendars.picker.css
djeu/static/djeu/css/jquery-calendars/humanity.calendars.picker.css
djeu/static/djeu/css/jquery-calendars/jquery.calendars.picker.css
djeu-0.2.1.dist-info/LICENSE
djeu-0.2.1.dist-info/METADATA
djeu-0.2.1.dist-info/WHEEL
djeu-0.2.1.dist-info/top_level.txt
djeu-0.2.1.dist-info/RECORD
