Metadata-Version: 2.1
Name: djeu
Version: 0.2.1
Summary: Some widgets collections fro the Django 4.0+
Home-page: https://github.com/usalko/djeu
Author: usalko
Author-email: ivict@rambler.ru
Maintainer: usalko
Maintainer-email: ivict@rambler.ru
License: APACHE 2.0
Platform: UNKNOWN
Classifier: Environment :: Web Environment
Classifier: Framework :: Django
Classifier: Intended Audience :: Developers
Classifier: License :: OSI Approved :: Apache Software License
Classifier: Operating System :: OS Independent
Classifier: Programming Language :: Python
Classifier: Programming Language :: Python :: 3.9
Classifier: Programming Language :: Python :: 3.10
Classifier: Topic :: Internet :: WWW/HTTP
Classifier: Topic :: Internet :: WWW/HTTP :: Dynamic Content
Classifier: Development Status :: 4 - Beta
License-File: LICENSE
Requires-Dist: Django (>=3.2)
Requires-Dist: django-static-jquery-ui (>=1.12.1.1)
